desker/__init__.py
desker/app.py
desker/settings.py
desker/utils.py
desker/faster_rcnn/__init__.py
desker/faster_rcnn/engine.py
desker/faster_rcnn/labels.json
desker/faster_rcnn/model.frcnn
desker/faster_rcnn/predict.py
desker/faster_rcnn/screen_data.py
desker/faster_rcnn/train.py
desker/faster_rcnn/transforms.py
desker/faster_rcnn/utils.py
desker/login/__init__.py
desker/login/cnn/__init__.py
desker/login/cnn/model.cnn
desker/login/cnn/predict.py
desker/login/cnn/train.py
desker/login/knn/__init__.py
desker/login/knn/model.knn
desker/login/knn/predict.py
desker/login/knn/train.py
desker/nlp/__init__.py
desker/nlp/utils.py
desker/nlp/algorithm/__init__.py
desker/nlp/algorithm/rake.py
desker/nlp/algorithm/text_rank.py
desker/nlp/corpus/__init__.py
desker/nlp/pipotron/__init__.py
desker/nlp/pipotron/bow.py
desker/nlp/pipotron/exceptions.py
desker/nlp/pipotron/selector.py
desker/nlp/pipotron/template.py
desker/nlp/pipotron/yaml_reader.py
desker/nlp/pipotron/templates/email.yml
desker/nlp/pipotron/templates/ena.yml
desker/nlp/pipotron/templates/example.yml
desker/nlp/pipotron/templates/excuses.yml
desker/nlp/pipotron/templates/laboralphy.yml
desker/nlp/pipotron/templates/pipo.yml
desker/ocr/__init__.py
desker/ocr/detect.py
desker/ocr/utils.py
desker-1.0a0.dist-info/LICENSE
desker-1.0a0.dist-info/METADATA
desker-1.0a0.dist-info/WHEEL
desker-1.0a0.dist-info/top_level.txt
desker-1.0a0.dist-info/RECORD
